Compiled from "UnityVideoEditor.kt"
public final class com.ocutech.editor.api.UnityVideoEditor {
  public static final com.ocutech.editor.api.UnityVideoEditor INSTANCE;

  private static final java.lang.String LIBRARY_VERSION;

  private static final int SCHEMA_VERSION;

  private static final java.lang.Object lock;

  private static volatile com.ocutech.editor.api.UnityVideoEditor$Runtime runtime;

  private static final java.util.List<java.lang.String> SUPPORTED_FEATURES;

  private com.ocutech.editor.api.UnityVideoEditor();
    Code:
       0: aload_0
       1: invokespecial #62                 // Method java/lang/Object."<init>":()V
       4: return

  public static final java.lang.String initialize(java.lang.String);
    Code:
       0: aload_0
       1: ldc           #68                 // String configJson
       3: invokestatic  #74                 // Method kotlin/jvm/internal/Intrinsics.checkNotNullParameter:(Ljava/lang/Object;Ljava/lang/String;)V
       6: getstatic     #76                 // Field INSTANCE:Lcom/ocutech/editor/api/UnityVideoEditor;
       9: astore_2
      10: nop
      11: getstatic     #82                 // Field kotlin/Result.Companion:Lkotlin/Result$Companion;
      14: pop
      15: aload_2
      16: astore_3
      17: iconst_0
      18: istore        4
      20: aload_0
      21: checkcast     #84                 // class java/lang/CharSequence
      24: invokestatic  #90                 // Method kotlin/text/StringsKt.isBlank:(Ljava/lang/CharSequence;)Z
      27: ifeq          46
      30: new           #92                 // class com/ocutech/editor/model/EditorConfig
      33: dup
      34: iconst_0
      35: iconst_0
      36: iconst_0
      37: bipush        7
      39: aconst_null
      40: invokespecial #95                 // Method com/ocutech/editor/model/EditorConfig."<init>":(IZZILkotlin/jvm/internal/DefaultConstructorMarker;)V
      43: goto          97
      46: getstatic     #102                // Field com/ocutech/editor/model/JsonCodec.INSTANCE:Lcom/ocutech/editor/model/JsonCodec;
      49: astore        5
      51: aload_0
      52: astore        6
      54: iconst_0
      55: istore        7
      57: aload         5
      59: invokevirtual #106                // Method com/ocutech/editor/model/JsonCodec.getJson:()Lkotlinx/serialization/json/Json;
      62: astore        8
      64: aload         6
      66: astore        9
      68: iconst_0
      69: istore        10
      71: aload         8
      73: aload         8
      75: invokevirtual #112                // Method kotlinx/serialization/json/Json.getSerializersModule:()Lkotlinx/serialization/modules/SerializersModule;
      78: pop
      79: getstatic     #115                // Field com/ocutech/editor/model/EditorConfig.Companion:Lcom/ocutech/editor/model/EditorConfig$Companion;
      82: invokevirtual #121                // Method com/ocutech/editor/model/EditorConfig$Companion.serializer:()Lkotlinx/serialization/KSerializer;
      85: checkcast     #123                // class kotlinx/serialization/DeserializationStrategy
      88: aload         9
      90: invokevirtual #127                // Method kotlinx/serialization/json/Json.decodeFromString:(Lkotlinx/serialization/DeserializationStrategy;Ljava/lang/String;)Ljava/lang/Object;
      93: nop
      94: checkcast     #92                 // class com/ocutech/editor/model/EditorConfig
      97: nop
      98: invokestatic  #131                // Method kotlin/Result."constructor-impl":(Ljava/lang/Object;)Ljava/lang/Object;
     101: astore_3
     102: goto          120
     105: astore        4
     107: getstatic     #82                 // Field kotlin/Result.Companion:Lkotlin/Result$Companion;
     110: pop
     111: aload         4
     113: invokestatic  #137                // Method kotlin/ResultKt.createFailure:(Ljava/lang/Throwable;)Ljava/lang/Object;
     116: invokestatic  #131                // Method kotlin/Result."constructor-impl":(Ljava/lang/Object;)Ljava/lang/Object;
     119: astore_3
     120: aload_3
     121: astore_2
     122: aload_2
     123: invokestatic  #141                // Method kotlin/Result."exceptionOrNull-impl":(Ljava/lang/Object;)Ljava/lang/Throwable;
     126: dup
     127: ifnonnull     135
     130: pop
     131: aload_2
     132: goto          232
     135: astore_3
     136: iconst_0
     137: istore        4
     139: getstatic     #102                // Field com/ocutech/editor/model/JsonCodec.INSTANCE:Lcom/ocutech/editor/model/JsonCodec;
     142: astore        5
     144: new           #143                // class com/ocutech/editor/model/InitializeResponse
     147: dup
     148: iconst_0
     149: ldc           #55                 // String 0.1.1-threadfix
     151: iconst_1
     152: aconst_null
     153: ldc           #145                // String invalid_config
     155: new           #147                // class com/ocutech/editor/model/ApiError
     158: dup
     159: ldc           #149                // String INVALID_CONFIG_JSON
     161: aload_3
     162: invokevirtual #153                // Method java/lang/Throwable.getMessage:()Ljava/lang/String;
     165: dup
     166: ifnonnull     172
     169: pop
     170: ldc           #155                // String Invalid config JSON.
     172: aload_3
     173: invokevirtual #159                // Method java/lang/Object.getClass:()Ljava/lang/Class;
     176: invokevirtual #164                // Method java/lang/Class.getName:()Ljava/lang/String;
     179: invokespecial #167                // Method com/ocutech/editor/model/ApiError."<init>":(Ljava/lang/String;Ljava/lang/String;Ljava/lang/String;)V
     182: bipush        8
     184: aconst_null
     185: invokespecial #170                // Method com/ocutech/editor/model/InitializeResponse."<init>":(ZLjava/lang/String;ILjava/util/List;Ljava/lang/String;Lcom/ocutech/editor/model/ApiError;ILkotlin/jvm/internal/DefaultConstructorMarker;)V
     188: astore        6
     190: nop
     191: iconst_0
     192: istore        7
     194: aload         5
     196: invokevirtual #106                // Method com/ocutech/editor/model/JsonCodec.getJson:()Lkotlinx/serialization/json/Json;
     199: astore        8
     201: aload         6
     203: astore        9
     205: iconst_0
     206: istore        10
     208: aload         8
     210: aload         8
     212: invokevirtual #112                // Method kotlinx/serialization/json/Json.getSerializersModule:()Lkotlinx/serialization/modules/SerializersModule;
     215: pop
     216: getstatic     #173                // Field com/ocutech/editor/model/InitializeResponse.Companion:Lcom/ocutech/editor/model/InitializeResponse$Companion;
     219: invokevirtual #176                // Method com/ocutech/editor/model/InitializeResponse$Companion.serializer:()Lkotlinx/serialization/KSerializer;
     222: checkcast     #178                // class kotlinx/serialization/SerializationStrategy
     225: aload         9
     227: invokevirtual #182                // Method kotlinx/serialization/json/Json.encodeToString:(Lkotlinx/serialization/SerializationStrategy;Ljava/lang/Object;)Ljava/lang/String;
     230: nop
     231: areturn
     232: checkcast     #92                 // class com/ocutech/editor/model/EditorConfig
     235: astore_1
     236: getstatic     #76                 // Field INSTANCE:Lcom/ocutech/editor/api/UnityVideoEditor;
     239: invokespecial #185                // Method resolveAppContext:()Landroid/content/Context;
     242: astore_2
     243: aload_2
     244: ifnonnull     325
     247: getstatic     #102                // Field com/ocutech/editor/model/JsonCodec.INSTANCE:Lcom/ocutech/editor/model/JsonCodec;
     250: astore_3
     251: new           #143                // class com/ocutech/editor/model/InitializeResponse
     254: dup
     255: iconst_0
     256: ldc           #55                 // String 0.1.1-threadfix
     258: iconst_1
     259: aconst_null
     260: ldc           #187                // String context_unavailable
     262: new           #147                // class com/ocutech/editor/model/ApiError
     265: dup
     266: ldc           #189                // String CONTEXT_UNAVAILABLE
     268: ldc           #191                // String Application context could not be resolved. Call initialize after Android runtime is ready.
     270: aconst_null
     271: iconst_4
     272: aconst_null
     273: invokespecial #194                // Method com/ocutech/editor/model/ApiError."<init>":(Ljava/lang/String;Ljava/lang/String;Ljava/lang/String;ILkotlin/jvm/internal/DefaultConstructorMarker;)V
     276: bipush        8
     278: aconst_null
     279: invokespecial #170                // Method com/ocutech/editor/model/InitializeResponse."<init>":(ZLjava/lang/String;ILjava/util/List;Ljava/lang/String;Lcom/ocutech/editor/model/ApiError;ILkotlin/jvm/internal/DefaultConstructorMarker;)V
     282: astore        4
     284: nop
     285: iconst_0
     286: istore        5
     288: aload_3
     289: invokevirtual #106                // Method com/ocutech/editor/model/JsonCodec.getJson:()Lkotlinx/serialization/json/Json;
     292: astore        6
     294: aload         4
     296: astore        7
     298: iconst_0
     299: istore        8
     301: aload         6
     303: aload         6
     305: invokevirtual #112                // Method kotlinx/serialization/json/Json.getSerializersModule:()Lkotlinx/serialization/modules/SerializersModule;
     308: pop
     309: getstatic     #173                // Field com/ocutech/editor/model/InitializeResponse.Companion:Lcom/ocutech/editor/model/InitializeResponse$Companion;
     312: invokevirtual #176                // Method com/ocutech/editor/model/InitializeResponse$Companion.serializer:()Lkotlinx/serialization/KSerializer;
     315: checkcast     #178                // class kotlinx/serialization/SerializationStrategy
     318: aload         7
     320: invokevirtual #182                // Method kotlinx/serialization/json/Json.encodeToString:(Lkotlinx/serialization/SerializationStrategy;Ljava/lang/Object;)Ljava/lang/String;
     323: nop
     324: areturn
     325: getstatic     #198                // Field lock:Ljava/lang/Object;
     328: astore        4
     330: aload         4
     332: monitorenter
     333: nop
     334: iconst_0
     335: istore        5
     337: getstatic     #76                 // Field INSTANCE:Lcom/ocutech/editor/api/UnityVideoEditor;
     340: pop
     341: new           #50                 // class com/ocutech/editor/api/UnityVideoEditor$Runtime
     344: dup
     345: aload_1
     346: new           #200                // class com/ocutech/editor/export/ExportJobManager
     349: dup
     350: aload_2
     351: new           #202                // class com/ocutech/editor/export/ExportRuntimeConfig
     354: dup
     355: ldc           #55                 // String 0.1.1-threadfix
     357: iconst_1
     358: aload_1
     359: invokevirtual #206                // Method com/ocutech/editor/model/EditorConfig.getKeepLastRequest:()Z
     362: aload_1
     363: invokevirtual #209                // Method com/ocutech/editor/model/EditorConfig.getDebugLogging:()Z
     366: invokespecial #212                // Method com/ocutech/editor/export/ExportRuntimeConfig."<init>":(Ljava/lang/String;IZZ)V
     369: aconst_null
     370: aconst_null
     371: aconst_null
     372: bipush        28
     374: aconst_null
     375: invokespecial #215                // Method com/ocutech/editor/export/ExportJobManager."<init>":(Landroid/content/Context;Lcom/ocutech/editor/export/ExportRuntimeConfig;Lcom/ocutech/editor/core/ProjectPlanner;Lcom/ocutech/editor/export/ExportExecutor;Lkotlinx/coroutines/CoroutineDispatcher;ILkotlin/jvm/internal/DefaultConstructorMarker;)V
     378: new           #217                // class com/ocutech/editor/core/ProjectPlanner
     381: dup
     382: invokespecial #218                // Method com/ocutech/editor/core/ProjectPlanner."<init>":()V
     385: aload_2
     386: invokespecial #221                // Method com/ocutech/editor/api/UnityVideoEditor$Runtime."<init>":(Lcom/ocutech/editor/model/EditorConfig;Lcom/ocutech/editor/export/ExportJobManager;Lcom/ocutech/editor/core/ProjectPlanner;Landroid/content/Context;)V
     389: putstatic     #223                // Field runtime:Lcom/ocutech/editor/api/UnityVideoEditor$Runtime;
     392: nop
     393: getstatic     #228                // Field kotlin/Unit.INSTANCE:Lkotlin/Unit;
     396: astore        5
     398: aload         4
     400: monitorexit
     401: goto          412
     404: astore        6
     406: aload         4
     408: monitorexit
     409: aload         6
     411: athrow
     412: getstatic     #102                // Field com/ocutech/editor/model/JsonCodec.INSTANCE:Lcom/ocutech/editor/model/JsonCodec;
     415: astore_3
     416: new           #143                // class com/ocutech/editor/model/InitializeResponse
     419: dup
     420: iconst_1
     421: ldc           #55                 // String 0.1.1-threadfix
     423: iconst_1
     424: getstatic     #230                // Field SUPPORTED_FEATURES:Ljava/util/List;
     427: ldc           #232                // String ready
     429: aconst_null
     430: bipush        32
     432: aconst_null
     433: invokespecial #170                // Method com/ocutech/editor/model/InitializeResponse."<init>":(ZLjava/lang/String;ILjava/util/List;Ljava/lang/String;Lcom/ocutech/editor/model/ApiError;ILkotlin/jvm/internal/DefaultConstructorMarker;)V
     436: astore        4
     438: nop
     439: iconst_0
     440: istore        5
     442: aload_3
     443: invokevirtual #106                // Method com/ocutech/editor/model/JsonCodec.getJson:()Lkotlinx/serialization/json/Json;
     446: astore        6
     448: aload         4
     450: astore        7
     452: iconst_0
     453: istore        8
     455: aload         6
     457: aload         6
     459: invokevirtual #112                // Method kotlinx/serialization/json/Json.getSerializersModule:()Lkotlinx/serialization/modules/SerializersModule;
     462: pop
     463: getstatic     #173                // Field com/ocutech/editor/model/InitializeResponse.Companion:Lcom/ocutech/editor/model/InitializeResponse$Companion;
     466: invokevirtual #176                // Method com/ocutech/editor/model/InitializeResponse$Companion.serializer:()Lkotlinx/serialization/KSerializer;
     469: checkcast     #178                // class kotlinx/serialization/SerializationStrategy
     472: aload         7
     474: invokevirtual #182                // Method kotlinx/serialization/json/Json.encodeToString:(Lkotlinx/serialization/SerializationStrategy;Ljava/lang/Object;)Ljava/lang/String;
     477: nop
     478: areturn
    Exception table:
       from    to  target type
          10   102   105   Class java/lang/Throwable
         333   398   404   any
         404   406   404   any

  public static final java.lang.String validateProject(java.lang.String);
    Code:
       0: aload_0
       1: ldc           #252                // String projectJson
       3: invokestatic  #74                 // Method kotlin/jvm/internal/Intrinsics.checkNotNullParameter:(Ljava/lang/Object;Ljava/lang/String;)V
       6: getstatic     #76                 // Field INSTANCE:Lcom/ocutech/editor/api/UnityVideoEditor;
       9: invokespecial #255                // Method ensureRuntime:()Lcom/ocutech/editor/api/UnityVideoEditor$Runtime;
      12: astore_1
      13: aload_1
      14: ifnonnull     24
      17: getstatic     #76                 // Field INSTANCE:Lcom/ocutech/editor/api/UnityVideoEditor;
      20: invokespecial #257                // Method notInitializedValidateResponse:()Ljava/lang/String;
      23: areturn
      24: getstatic     #76                 // Field INSTANCE:Lcom/ocutech/editor/api/UnityVideoEditor;
      27: aload_0
      28: invokespecial #260                // Method parseProject:(Ljava/lang/String;)Lcom/ocutech/editor/model/EditorProjectDocument;
      31: dup
      32: ifnonnull     43
      35: pop
      36: getstatic     #76                 // Field INSTANCE:Lcom/ocutech/editor/api/UnityVideoEditor;
      39: invokespecial #262                // Method invalidProjectValidateResponse:()Ljava/lang/String;
      42: areturn
      43: astore_2
      44: aload_1
      45: invokevirtual #268                // Method com/ocutech/editor/api/UnityVideoEditor$Runtime.getPlanner:()Lcom/ocutech/editor/core/ProjectPlanner;
      48: aload_2
      49: invokevirtual #272                // Method com/ocutech/editor/core/ProjectPlanner.validate:(Lcom/ocutech/editor/model/EditorProjectDocument;)Lcom/ocutech/editor/model/ValidationReport;
      52: astore_3
      53: getstatic     #277                // Field com/ocutech/editor/export/ProjectUriAccessValidator.INSTANCE:Lcom/ocutech/editor/export/ProjectUriAccessValidator;
      56: aload_1
      57: invokevirtual #280                // Method com/ocutech/editor/api/UnityVideoEditor$Runtime.getContext:()Landroid/content/Context;
      60: aload_2
      61: invokevirtual #283                // Method com/ocutech/editor/export/ProjectUriAccessValidator.validate:(Landroid/content/Context;Lcom/ocutech/editor/model/EditorProjectDocument;)Ljava/util/List;
      64: astore        4
      66: aload_3
      67: aload_3
      68: invokevirtual #289                // Method com/ocutech/editor/model/ValidationReport.getErrors:()Ljava/util/List;
      71: checkcast     #291                // class java/util/Collection
      74: aload         4
      76: checkcast     #293                // class java/lang/Iterable
      79: invokestatic  #299                // Method kotlin/collections/CollectionsKt.plus:(Ljava/util/Collection;Ljava/lang/Iterable;)Ljava/util/List;
      82: aconst_null
      83: aconst_null
      84: lconst_0
      85: bipush        14
      87: aconst_null
      88: invokestatic  #303                // Method com/ocutech/editor/model/ValidationReport.copy$default:(Lcom/ocutech/editor/model/ValidationReport;Ljava/util/List;Ljava/util/List;Ljava/util/List;JILjava/lang/Object;)Lcom/ocutech/editor/model/ValidationReport;
      91: astore        5
      93: getstatic     #102                // Field com/ocutech/editor/model/JsonCodec.INSTANCE:Lcom/ocutech/editor/model/JsonCodec;
      96: astore        6
      98: new           #305                // class com/ocutech/editor/model/ValidateProjectResponse
     101: dup
     102: aload         5
     104: invokevirtual #289                // Method com/ocutech/editor/model/ValidationReport.getErrors:()Ljava/util/List;
     107: invokeinterface #310,  1          // InterfaceMethod java/util/List.isEmpty:()Z
     112: ldc           #55                 // String 0.1.1-threadfix
     114: iconst_1
     115: aload         5
     117: aconst_null
     118: bipush        16
     120: aconst_null
     121: invokespecial #313                // Method com/ocutech/editor/model/ValidateProjectResponse."<init>":(ZLjava/lang/String;ILcom/ocutech/editor/model/ValidationReport;Lcom/ocutech/editor/model/ApiError;ILkotlin/jvm/internal/DefaultConstructorMarker;)V
     124: astore        7
     126: nop
     127: iconst_0
     128: istore        8
     130: aload         6
     132: invokevirtual #106                // Method com/ocutech/editor/model/JsonCodec.getJson:()Lkotlinx/serialization/json/Json;
     135: astore        9
     137: aload         7
     139: astore        10
     141: iconst_0
     142: istore        11
     144: aload         9
     146: aload         9
     148: invokevirtual #112                // Method kotlinx/serialization/json/Json.getSerializersModule:()Lkotlinx/serialization/modules/SerializersModule;
     151: pop
     152: getstatic     #316                // Field com/ocutech/editor/model/ValidateProjectResponse.Companion:Lcom/ocutech/editor/model/ValidateProjectResponse$Companion;
     155: invokevirtual #319                // Method com/ocutech/editor/model/ValidateProjectResponse$Companion.serializer:()Lkotlinx/serialization/KSerializer;
     158: checkcast     #178                // class kotlinx/serialization/SerializationStrategy
     161: aload         10
     163: invokevirtual #182                // Method kotlinx/serialization/json/Json.encodeToString:(Lkotlinx/serialization/SerializationStrategy;Ljava/lang/Object;)Ljava/lang/String;
     166: nop
     167: areturn

  public static final java.lang.String startExport(java.lang.String);
    Code:
       0: aload_0
       1: ldc           #252                // String projectJson
       3: invokestatic  #74                 // Method kotlin/jvm/internal/Intrinsics.checkNotNullParameter:(Ljava/lang/Object;Ljava/lang/String;)V
       6: getstatic     #76                 // Field INSTANCE:Lcom/ocutech/editor/api/UnityVideoEditor;
       9: invokespecial #255                // Method ensureRuntime:()Lcom/ocutech/editor/api/UnityVideoEditor$Runtime;
      12: dup
      13: ifnonnull     97
      16: pop
      17: getstatic     #102                // Field com/ocutech/editor/model/JsonCodec.INSTANCE:Lcom/ocutech/editor/model/JsonCodec;
      20: astore_3
      21: new           #327                // class com/ocutech/editor/model/StartExportResponse
      24: dup
      25: iconst_0
      26: ldc           #55                 // String 0.1.1-threadfix
      28: iconst_1
      29: aconst_null
      30: iconst_0
      31: aconst_null
      32: new           #147                // class com/ocutech/editor/model/ApiError
      35: dup
      36: ldc_w         #329                // String NOT_INITIALIZED
      39: ldc_w         #331                // String Call initialize() before startExport().
      42: aconst_null
      43: iconst_4
      44: aconst_null
      45: invokespecial #194                // Method com/ocutech/editor/model/ApiError."<init>":(Ljava/lang/String;Ljava/lang/String;Ljava/lang/String;ILkotlin/jvm/internal/DefaultConstructorMarker;)V
      48: bipush        40
      50: aconst_null
      51: invokespecial #334                // Method com/ocutech/editor/model/StartExportResponse."<init>":(ZLjava/lang/String;ILjava/lang/String;ZLcom/ocutech/editor/model/JobStatus;Lcom/ocutech/editor/model/ApiError;ILkotlin/jvm/internal/DefaultConstructorMarker;)V
      54: astore        4
      56: nop
      57: iconst_0
      58: istore        5
      60: aload_3
      61: invokevirtual #106                // Method com/ocutech/editor/model/JsonCodec.getJson:()Lkotlinx/serialization/json/Json;
      64: astore        6
      66: aload         4
      68: astore        7
      70: iconst_0
      71: istore        8
      73: aload         6
      75: aload         6
      77: invokevirtual #112                // Method kotlinx/serialization/json/Json.getSerializersModule:()Lkotlinx/serialization/modules/SerializersModule;
      80: pop
      81: getstatic     #337                // Field com/ocutech/editor/model/StartExportResponse.Companion:Lcom/ocutech/editor/model/StartExportResponse$Companion;
      84: invokevirtual #340                // Method com/ocutech/editor/model/StartExportResponse$Companion.serializer:()Lkotlinx/serialization/KSerializer;
      87: checkcast     #178                // class kotlinx/serialization/SerializationStrategy
      90: aload         7
      92: invokevirtual #182                // Method kotlinx/serialization/json/Json.encodeToString:(Lkotlinx/serialization/SerializationStrategy;Ljava/lang/Object;)Ljava/lang/String;
      95: nop
      96: areturn
      97: astore_1
      98: getstatic     #76                 // Field INSTANCE:Lcom/ocutech/editor/api/UnityVideoEditor;
     101: aload_0
     102: invokespecial #260                // Method parseProject:(Ljava/lang/String;)Lcom/ocutech/editor/model/EditorProjectDocument;
     105: dup
     106: ifnonnull     192
     109: pop
     110: getstatic     #102                // Field com/ocutech/editor/model/JsonCodec.INSTANCE:Lcom/ocutech/editor/model/JsonCodec;
     113: astore        4
     115: new           #327                // class com/ocutech/editor/model/StartExportResponse
     118: dup
     119: iconst_0
     120: ldc           #55                 // String 0.1.1-threadfix
     122: iconst_1
     123: aconst_null
     124: iconst_0
     125: aconst_null
     126: new           #147                // class com/ocutech/editor/model/ApiError
     129: dup
     130: ldc_w         #342                // String INVALID_PROJECT_JSON
     133: ldc_w         #344                // String Project JSON is malformed.
     136: aconst_null
     137: iconst_4
     138: aconst_null
     139: invokespecial #194                // Method com/ocutech/editor/model/ApiError."<init>":(Ljava/lang/String;Ljava/lang/String;Ljava/lang/String;ILkotlin/jvm/internal/DefaultConstructorMarker;)V
     142: bipush        40
     144: aconst_null
     145: invokespecial #334                // Method com/ocutech/editor/model/StartExportResponse."<init>":(ZLjava/lang/String;ILjava/lang/String;ZLcom/ocutech/editor/model/JobStatus;Lcom/ocutech/editor/model/ApiError;ILkotlin/jvm/internal/DefaultConstructorMarker;)V
     148: astore        5
     150: nop
     151: iconst_0
     152: istore        6
     154: aload         4
     156: invokevirtual #106                // Method com/ocutech/editor/model/JsonCodec.getJson:()Lkotlinx/serialization/json/Json;
     159: astore        7
     161: aload         5
     163: astore        8
     165: iconst_0
     166: istore        9
     168: aload         7
     170: aload         7
     172: invokevirtual #112                // Method kotlinx/serialization/json/Json.getSerializersModule:()Lkotlinx/serialization/modules/SerializersModule;
     175: pop
     176: getstatic     #337                // Field com/ocutech/editor/model/StartExportResponse.Companion:Lcom/ocutech/editor/model/StartExportResponse$Companion;
     179: invokevirtual #340                // Method com/ocutech/editor/model/StartExportResponse$Companion.serializer:()Lkotlinx/serialization/KSerializer;
     182: checkcast     #178                // class kotlinx/serialization/SerializationStrategy
     185: aload         8
     187: invokevirtual #182                // Method kotlinx/serialization/json/Json.encodeToString:(Lkotlinx/serialization/SerializationStrategy;Ljava/lang/Object;)Ljava/lang/String;
     190: nop
     191: areturn
     192: astore_2
     193: getstatic     #277                // Field com/ocutech/editor/export/ProjectUriAccessValidator.INSTANCE:Lcom/ocutech/editor/export/ProjectUriAccessValidator;
     196: aload_1
     197: invokevirtual #280                // Method com/ocutech/editor/api/UnityVideoEditor$Runtime.getContext:()Landroid/content/Context;
     200: aload_2
     201: invokevirtual #283                // Method com/ocutech/editor/export/ProjectUriAccessValidator.validate:(Landroid/content/Context;Lcom/ocutech/editor/model/EditorProjectDocument;)Ljava/util/List;
     204: astore_3
     205: aload_3
     206: checkcast     #291                // class java/util/Collection
     209: invokeinterface #345,  1          // InterfaceMethod java/util/Collection.isEmpty:()Z
     214: ifne          221
     217: iconst_1
     218: goto          222
     221: iconst_0
     222: ifeq          314
     225: getstatic     #102                // Field com/ocutech/editor/model/JsonCodec.INSTANCE:Lcom/ocutech/editor/model/JsonCodec;
     228: astore        4
     230: new           #327                // class com/ocutech/editor/model/StartExportResponse
     233: dup
     234: iconst_0
     235: ldc           #55                 // String 0.1.1-threadfix
     237: iconst_1
     238: aconst_null
     239: iconst_0
     240: aconst_null
     241: new           #147                // class com/ocutech/editor/model/ApiError
     244: dup
     245: ldc_w         #347                // String PROJECT_URI_VALIDATION_FAILED
     248: aload_3
     249: invokestatic  #351                // Method kotlin/collections/CollectionsKt.first:(Ljava/util/List;)Ljava/lang/Object;
     252: checkcast     #353                // class com/ocutech/editor/model/ValidationIssue
     255: invokevirtual #354                // Method com/ocutech/editor/model/ValidationIssue.getMessage:()Ljava/lang/String;
     258: aconst_null
     259: iconst_4
     260: aconst_null
     261: invokespecial #194                // Method com/ocutech/editor/model/ApiError."<init>":(Ljava/lang/String;Ljava/lang/String;Ljava/lang/String;ILkotlin/jvm/internal/DefaultConstructorMarker;)V
     264: bipush        40
     266: aconst_null
     267: invokespecial #334                // Method com/ocutech/editor/model/StartExportResponse."<init>":(ZLjava/lang/String;ILjava/lang/String;ZLcom/ocutech/editor/model/JobStatus;Lcom/ocutech/editor/model/ApiError;ILkotlin/jvm/internal/DefaultConstructorMarker;)V
     270: astore        5
     272: nop
     273: iconst_0
     274: istore        6
     276: aload         4
     278: invokevirtual #106                // Method com/ocutech/editor/model/JsonCodec.getJson:()Lkotlinx/serialization/json/Json;
     281: astore        7
     283: aload         5
     285: astore        8
     287: iconst_0
     288: istore        9
     290: aload         7
     292: aload         7
     294: invokevirtual #112                // Method kotlinx/serialization/json/Json.getSerializersModule:()Lkotlinx/serialization/modules/SerializersModule;
     297: pop
     298: getstatic     #337                // Field com/ocutech/editor/model/StartExportResponse.Companion:Lcom/ocutech/editor/model/StartExportResponse$Companion;
     301: invokevirtual #340                // Method com/ocutech/editor/model/StartExportResponse$Companion.serializer:()Lkotlinx/serialization/KSerializer;
     304: checkcast     #178                // class kotlinx/serialization/SerializationStrategy
     307: aload         8
     309: invokevirtual #182                // Method kotlinx/serialization/json/Json.encodeToString:(Lkotlinx/serialization/SerializationStrategy;Ljava/lang/Object;)Ljava/lang/String;
     312: nop
     313: areturn
     314: aload_1
     315: invokevirtual #358                // Method com/ocutech/editor/api/UnityVideoEditor$Runtime.getManager:()Lcom/ocutech/editor/export/ExportJobManager;
     318: aload_0
     319: aload_2
     320: invokevirtual #361                // Method com/ocutech/editor/export/ExportJobManager.startExport:(Ljava/lang/String;Lcom/ocutech/editor/model/EditorProjectDocument;)Ljava/lang/String;
     323: astore        4
     325: getstatic     #102                // Field com/ocutech/editor/model/JsonCodec.INSTANCE:Lcom/ocutech/editor/model/JsonCodec;
     328: astore        5
     330: new           #327                // class com/ocutech/editor/model/StartExportResponse
     333: dup
     334: iconst_1
     335: ldc           #55                 // String 0.1.1-threadfix
     337: iconst_1
     338: aload         4
     340: iconst_1
     341: getstatic     #367                // Field com/ocutech/editor/model/JobStatus.QUEUED:Lcom/ocutech/editor/model/JobStatus;
     344: aconst_null
     345: bipush        64
     347: aconst_null
     348: invokespecial #334                // Method com/ocutech/editor/model/StartExportResponse."<init>":(ZLjava/lang/String;ILjava/lang/String;ZLcom/ocutech/editor/model/JobStatus;Lcom/ocutech/editor/model/ApiError;ILkotlin/jvm/internal/DefaultConstructorMarker;)V
     351: astore        6
     353: nop
     354: iconst_0
     355: istore        7
     357: aload         5
     359: invokevirtual #106                // Method com/ocutech/editor/model/JsonCodec.getJson:()Lkotlinx/serialization/json/Json;
     362: astore        8
     364: aload         6
     366: astore        9
     368: iconst_0
     369: istore        10
     371: aload         8
     373: aload         8
     375: invokevirtual #112                // Method kotlinx/serialization/json/Json.getSerializersModule:()Lkotlinx/serialization/modules/SerializersModule;
     378: pop
     379: getstatic     #337                // Field com/ocutech/editor/model/StartExportResponse.Companion:Lcom/ocutech/editor/model/StartExportResponse$Companion;
     382: invokevirtual #340                // Method com/ocutech/editor/model/StartExportResponse$Companion.serializer:()Lkotlinx/serialization/KSerializer;
     385: checkcast     #178                // class kotlinx/serialization/SerializationStrategy
     388: aload         9
     390: invokevirtual #182                // Method kotlinx/serialization/json/Json.encodeToString:(Lkotlinx/serialization/SerializationStrategy;Ljava/lang/Object;)Ljava/lang/String;
     393: nop
     394: areturn

  public static final java.lang.String getJobState(java.lang.String);
    Code:
       0: aload_0
       1: ldc_w         #368                // String jobId
       4: invokestatic  #74                 // Method kotlin/jvm/internal/Intrinsics.checkNotNullParameter:(Ljava/lang/Object;Ljava/lang/String;)V
       7: getstatic     #76                 // Field INSTANCE:Lcom/ocutech/editor/api/UnityVideoEditor;
      10: invokespecial #255                // Method ensureRuntime:()Lcom/ocutech/editor/api/UnityVideoEditor$Runtime;
      13: dup
      14: ifnonnull     96
      17: pop
      18: getstatic     #102                // Field com/ocutech/editor/model/JsonCodec.INSTANCE:Lcom/ocutech/editor/model/JsonCodec;
      21: astore_3
      22: new           #370                // class com/ocutech/editor/model/JobStateResponse
      25: dup
      26: iconst_0
      27: ldc           #55                 // String 0.1.1-threadfix
      29: iconst_1
      30: aconst_null
      31: new           #147                // class com/ocutech/editor/model/ApiError
      34: dup
      35: ldc_w         #329                // String NOT_INITIALIZED
      38: ldc_w         #372                // String Call initialize() before getJobState().
      41: aconst_null
      42: iconst_4
      43: aconst_null
      44: invokespecial #194                // Method com/ocutech/editor/model/ApiError."<init>":(Ljava/lang/String;Ljava/lang/String;Ljava/lang/String;ILkotlin/jvm/internal/DefaultConstructorMarker;)V
      47: bipush        8
      49: aconst_null
      50: invokespecial #375                // Method com/ocutech/editor/model/JobStateResponse."<init>":(ZLjava/lang/String;ILcom/ocutech/editor/model/JobStatePayload;Lcom/ocutech/editor/model/ApiError;ILkotlin/jvm/internal/DefaultConstructorMarker;)V
      53: astore        4
      55: nop
      56: iconst_0
      57: istore        5
      59: aload_3
      60: invokevirtual #106                // Method com/ocutech/editor/model/JsonCodec.getJson:()Lkotlinx/serialization/json/Json;
      63: astore        6
      65: aload         4
      67: astore        7
      69: iconst_0
      70: istore        8
      72: aload         6
      74: aload         6
      76: invokevirtual #112                // Method kotlinx/serialization/json/Json.getSerializersModule:()Lkotlinx/serialization/modules/SerializersModule;
      79: pop
      80: getstatic     #378                // Field com/ocutech/editor/model/JobStateResponse.Companion:Lcom/ocutech/editor/model/JobStateResponse$Companion;
      83: invokevirtual #381                // Method com/ocutech/editor/model/JobStateResponse$Companion.serializer:()Lkotlinx/serialization/KSerializer;
      86: checkcast     #178                // class kotlinx/serialization/SerializationStrategy
      89: aload         7
      91: invokevirtual #182                // Method kotlinx/serialization/json/Json.encodeToString:(Lkotlinx/serialization/SerializationStrategy;Ljava/lang/Object;)Ljava/lang/String;
      94: nop
      95: areturn
      96: astore_1
      97: aload_1
      98: invokevirtual #358                // Method com/ocutech/editor/api/UnityVideoEditor$Runtime.getManager:()Lcom/ocutech/editor/export/ExportJobManager;
     101: aload_0
     102: invokevirtual #385                // Method com/ocutech/editor/export/ExportJobManager.getState:(Ljava/lang/String;)Lcom/ocutech/editor/model/JobStatePayload;
     105: astore_2
     106: aload_2
     107: ifnonnull     193
     110: getstatic     #102                // Field com/ocutech/editor/model/JsonCodec.INSTANCE:Lcom/ocutech/editor/model/JsonCodec;
     113: astore_3
     114: new           #370                // class com/ocutech/editor/model/JobStateResponse
     117: dup
     118: iconst_0
     119: ldc           #55                 // String 0.1.1-threadfix
     121: iconst_1
     122: aconst_null
     123: new           #147                // class com/ocutech/editor/model/ApiError
     126: dup
     127: ldc_w         #387                // String JOB_NOT_FOUND
     130: aload_0
     131: invokedynamic #398,  0            // InvokeDynamic #0:makeConcatWithConstants:(Ljava/lang/String;)Ljava/lang/String;
     136: aconst_null
     137: iconst_4
     138: aconst_null
     139: invokespecial #194                // Method com/ocutech/editor/model/ApiError."<init>":(Ljava/lang/String;Ljava/lang/String;Ljava/lang/String;ILkotlin/jvm/internal/DefaultConstructorMarker;)V
     142: bipush        8
     144: aconst_null
     145: invokespecial #375                // Method com/ocutech/editor/model/JobStateResponse."<init>":(ZLjava/lang/String;ILcom/ocutech/editor/model/JobStatePayload;Lcom/ocutech/editor/model/ApiError;ILkotlin/jvm/internal/DefaultConstructorMarker;)V
     148: astore        4
     150: nop
     151: iconst_0
     152: istore        5
     154: aload_3
     155: invokevirtual #106                // Method com/ocutech/editor/model/JsonCodec.getJson:()Lkotlinx/serialization/json/Json;
     158: astore        6
     160: aload         4
     162: astore        7
     164: iconst_0
     165: istore        8
     167: aload         6
     169: aload         6
     171: invokevirtual #112                // Method kotlinx/serialization/json/Json.getSerializersModule:()Lkotlinx/serialization/modules/SerializersModule;
     174: pop
     175: getstatic     #378                // Field com/ocutech/editor/model/JobStateResponse.Companion:Lcom/ocutech/editor/model/JobStateResponse$Companion;
     178: invokevirtual #381                // Method com/ocutech/editor/model/JobStateResponse$Companion.serializer:()Lkotlinx/serialization/KSerializer;
     181: checkcast     #178                // class kotlinx/serialization/SerializationStrategy
     184: aload         7
     186: invokevirtual #182                // Method kotlinx/serialization/json/Json.encodeToString:(Lkotlinx/serialization/SerializationStrategy;Ljava/lang/Object;)Ljava/lang/String;
     189: nop
     190: goto          255
     193: getstatic     #102                // Field com/ocutech/editor/model/JsonCodec.INSTANCE:Lcom/ocutech/editor/model/JsonCodec;
     196: astore_3
     197: new           #370                // class com/ocutech/editor/model/JobStateResponse
     200: dup
     201: iconst_1
     202: ldc           #55                 // String 0.1.1-threadfix
     204: iconst_1
     205: aload_2
     206: aconst_null
     207: bipush        16
     209: aconst_null
     210: invokespecial #375                // Method com/ocutech/editor/model/JobStateResponse."<init>":(ZLjava/lang/String;ILcom/ocutech/editor/model/JobStatePayload;Lcom/ocutech/editor/model/ApiError;ILkotlin/jvm/internal/DefaultConstructorMarker;)V
     213: astore        4
     215: nop
     216: iconst_0
     217: istore        5
     219: aload_3
     220: invokevirtual #106                // Method com/ocutech/editor/model/JsonCodec.getJson:()Lkotlinx/serialization/json/Json;
     223: astore        6
     225: aload         4
     227: astore        7
     229: iconst_0
     230: istore        8
     232: aload         6
     234: aload         6
     236: invokevirtual #112                // Method kotlinx/serialization/json/Json.getSerializersModule:()Lkotlinx/serialization/modules/SerializersModule;
     239: pop
     240: getstatic     #378                // Field com/ocutech/editor/model/JobStateResponse.Companion:Lcom/ocutech/editor/model/JobStateResponse$Companion;
     243: invokevirtual #381                // Method com/ocutech/editor/model/JobStateResponse$Companion.serializer:()Lkotlinx/serialization/KSerializer;
     246: checkcast     #178                // class kotlinx/serialization/SerializationStrategy
     249: aload         7
     251: invokevirtual #182                // Method kotlinx/serialization/json/Json.encodeToString:(Lkotlinx/serialization/SerializationStrategy;Ljava/lang/Object;)Ljava/lang/String;
     254: nop
     255: areturn

  public static final java.lang.String cancelJob(java.lang.String);
    Code:
       0: aload_0
       1: ldc_w         #368                // String jobId
       4: invokestatic  #74                 // Method kotlin/jvm/internal/Intrinsics.checkNotNullParameter:(Ljava/lang/Object;Ljava/lang/String;)V
       7: getstatic     #76                 // Field INSTANCE:Lcom/ocutech/editor/api/UnityVideoEditor;
      10: invokespecial #255                // Method ensureRuntime:()Lcom/ocutech/editor/api/UnityVideoEditor$Runtime;
      13: dup
      14: ifnonnull     96
      17: pop
      18: getstatic     #102                // Field com/ocutech/editor/model/JsonCodec.INSTANCE:Lcom/ocutech/editor/model/JsonCodec;
      21: astore_3
      22: new           #404                // class com/ocutech/editor/model/AckResponse
      25: dup
      26: iconst_0
      27: ldc           #55                 // String 0.1.1-threadfix
      29: iconst_1
      30: iconst_0
      31: ldc_w         #406                // String Call initialize() before cancelJob().
      34: new           #147                // class com/ocutech/editor/model/ApiError
      37: dup
      38: ldc_w         #329                // String NOT_INITIALIZED
      41: ldc_w         #406                // String Call initialize() before cancelJob().
      44: aconst_null
      45: iconst_4
      46: aconst_null
      47: invokespecial #194                // Method com/ocutech/editor/model/ApiError."<init>":(Ljava/lang/String;Ljava/lang/String;Ljava/lang/String;ILkotlin/jvm/internal/DefaultConstructorMarker;)V
      50: invokespecial #409                // Method com/ocutech/editor/model/AckResponse."<init>":(ZLjava/lang/String;IZLjava/lang/String;Lcom/ocutech/editor/model/ApiError;)V
      53: astore        4
      55: nop
      56: iconst_0
      57: istore        5
      59: aload_3
      60: invokevirtual #106                // Method com/ocutech/editor/model/JsonCodec.getJson:()Lkotlinx/serialization/json/Json;
      63: astore        6
      65: aload         4
      67: astore        7
      69: iconst_0
      70: istore        8
      72: aload         6
      74: aload         6
      76: invokevirtual #112                // Method kotlinx/serialization/json/Json.getSerializersModule:()Lkotlinx/serialization/modules/SerializersModule;
      79: pop
      80: getstatic     #412                // Field com/ocutech/editor/model/AckResponse.Companion:Lcom/ocutech/editor/model/AckResponse$Companion;
      83: invokevirtual #415                // Method com/ocutech/editor/model/AckResponse$Companion.serializer:()Lkotlinx/serialization/KSerializer;
      86: checkcast     #178                // class kotlinx/serialization/SerializationStrategy
      89: aload         7
      91: invokevirtual #182                // Method kotlinx/serialization/json/Json.encodeToString:(Lkotlinx/serialization/SerializationStrategy;Ljava/lang/Object;)Ljava/lang/String;
      94: nop
      95: areturn
      96: astore_1
      97: aload_1
      98: invokevirtual #358                // Method com/ocutech/editor/api/UnityVideoEditor$Runtime.getManager:()Lcom/ocutech/editor/export/ExportJobManager;
     101: aload_0
     102: invokevirtual #418                // Method com/ocutech/editor/export/ExportJobManager.cancelJob:(Ljava/lang/String;)Z
     105: istore_2
     106: getstatic     #102                // Field com/ocutech/editor/model/JsonCodec.INSTANCE:Lcom/ocutech/editor/model/JsonCodec;
     109: astore_3
     110: new           #404                // class com/ocutech/editor/model/AckResponse
     113: dup
     114: iload_2
     115: ldc           #55                 // String 0.1.1-threadfix
     117: iconst_1
     118: iload_2
     119: iload_2
     120: ifeq          129
     123: ldc_w         #420                // String Cancellation requested.
     126: goto          132
     129: ldc_w         #422                // String Job not found.
     132: iload_2
     133: ifeq          140
     136: aconst_null
     137: goto          159
     140: new           #147                // class com/ocutech/editor/model/ApiError
     143: dup
     144: ldc_w         #387                // String JOB_NOT_FOUND
     147: aload_0
     148: invokedynamic #398,  0            // InvokeDynamic #0:makeConcatWithConstants:(Ljava/lang/String;)Ljava/lang/String;
     153: aconst_null
     154: iconst_4
     155: aconst_null
     156: invokespecial #194                // Method com/ocutech/editor/model/ApiError."<init>":(Ljava/lang/String;Ljava/lang/String;Ljava/lang/String;ILkotlin/jvm/internal/DefaultConstructorMarker;)V
     159: invokespecial #409                // Method com/ocutech/editor/model/AckResponse."<init>":(ZLjava/lang/String;IZLjava/lang/String;Lcom/ocutech/editor/model/ApiError;)V
     162: astore        4
     164: nop
     165: iconst_0
     166: istore        5
     168: aload_3
     169: invokevirtual #106                // Method com/ocutech/editor/model/JsonCodec.getJson:()Lkotlinx/serialization/json/Json;
     172: astore        6
     174: aload         4
     176: astore        7
     178: iconst_0
     179: istore        8
     181: aload         6
     183: aload         6
     185: invokevirtual #112                // Method kotlinx/serialization/json/Json.getSerializersModule:()Lkotlinx/serialization/modules/SerializersModule;
     188: pop
     189: getstatic     #412                // Field com/ocutech/editor/model/AckResponse.Companion:Lcom/ocutech/editor/model/AckResponse$Companion;
     192: invokevirtual #415                // Method com/ocutech/editor/model/AckResponse$Companion.serializer:()Lkotlinx/serialization/KSerializer;
     195: checkcast     #178                // class kotlinx/serialization/SerializationStrategy
     198: aload         7
     200: invokevirtual #182                // Method kotlinx/serialization/json/Json.encodeToString:(Lkotlinx/serialization/SerializationStrategy;Ljava/lang/Object;)Ljava/lang/String;
     203: nop
     204: areturn

  public static final java.lang.String releaseJob(java.lang.String);
    Code:
       0: aload_0
       1: ldc_w         #368                // String jobId
       4: invokestatic  #74                 // Method kotlin/jvm/internal/Intrinsics.checkNotNullParameter:(Ljava/lang/Object;Ljava/lang/String;)V
       7: getstatic     #76                 // Field INSTANCE:Lcom/ocutech/editor/api/UnityVideoEditor;
      10: invokespecial #255                // Method ensureRuntime:()Lcom/ocutech/editor/api/UnityVideoEditor$Runtime;
      13: dup
      14: ifnonnull     96
      17: pop
      18: getstatic     #102                // Field com/ocutech/editor/model/JsonCodec.INSTANCE:Lcom/ocutech/editor/model/JsonCodec;
      21: astore_3
      22: new           #404                // class com/ocutech/editor/model/AckResponse
      25: dup
      26: iconst_0
      27: ldc           #55                 // String 0.1.1-threadfix
      29: iconst_1
      30: iconst_0
      31: ldc_w         #426                // String Call initialize() before releaseJob().
      34: new           #147                // class com/ocutech/editor/model/ApiError
      37: dup
      38: ldc_w         #329                // String NOT_INITIALIZED
      41: ldc_w         #426                // String Call initialize() before releaseJob().
      44: aconst_null
      45: iconst_4
      46: aconst_null
      47: invokespecial #194                // Method com/ocutech/editor/model/ApiError."<init>":(Ljava/lang/String;Ljava/lang/String;Ljava/lang/String;ILkotlin/jvm/internal/DefaultConstructorMarker;)V
      50: invokespecial #409                // Method com/ocutech/editor/model/AckResponse."<init>":(ZLjava/lang/String;IZLjava/lang/String;Lcom/ocutech/editor/model/ApiError;)V
      53: astore        4
      55: nop
      56: iconst_0
      57: istore        5
      59: aload_3
      60: invokevirtual #106                // Method com/ocutech/editor/model/JsonCodec.getJson:()Lkotlinx/serialization/json/Json;
      63: astore        6
      65: aload         4
      67: astore        7
      69: iconst_0
      70: istore        8
      72: aload         6
      74: aload         6
      76: invokevirtual #112                // Method kotlinx/serialization/json/Json.getSerializersModule:()Lkotlinx/serialization/modules/SerializersModule;
      79: pop
      80: getstatic     #412                // Field com/ocutech/editor/model/AckResponse.Companion:Lcom/ocutech/editor/model/AckResponse$Companion;
      83: invokevirtual #415                // Method com/ocutech/editor/model/AckResponse$Companion.serializer:()Lkotlinx/serialization/KSerializer;
      86: checkcast     #178                // class kotlinx/serialization/SerializationStrategy
      89: aload         7
      91: invokevirtual #182                // Method kotlinx/serialization/json/Json.encodeToString:(Lkotlinx/serialization/SerializationStrategy;Ljava/lang/Object;)Ljava/lang/String;
      94: nop
      95: areturn
      96: astore_1
      97: aload_1
      98: invokevirtual #358                // Method com/ocutech/editor/api/UnityVideoEditor$Runtime.getManager:()Lcom/ocutech/editor/export/ExportJobManager;
     101: aload_0
     102: invokevirtual #428                // Method com/ocutech/editor/export/ExportJobManager.releaseJob:(Ljava/lang/String;)Z
     105: istore_2
     106: getstatic     #102                // Field com/ocutech/editor/model/JsonCodec.INSTANCE:Lcom/ocutech/editor/model/JsonCodec;
     109: astore_3
     110: new           #404                // class com/ocutech/editor/model/AckResponse
     113: dup
     114: iload_2
     115: ldc           #55                 // String 0.1.1-threadfix
     117: iconst_1
     118: iload_2
     119: iload_2
     120: ifeq          129
     123: ldc_w         #430                // String Job released.
     126: goto          132
     129: ldc_w         #422                // String Job not found.
     132: iload_2
     133: ifeq          140
     136: aconst_null
     137: goto          159
     140: new           #147                // class com/ocutech/editor/model/ApiError
     143: dup
     144: ldc_w         #387                // String JOB_NOT_FOUND
     147: aload_0
     148: invokedynamic #398,  0            // InvokeDynamic #0:makeConcatWithConstants:(Ljava/lang/String;)Ljava/lang/String;
     153: aconst_null
     154: iconst_4
     155: aconst_null
     156: invokespecial #194                // Method com/ocutech/editor/model/ApiError."<init>":(Ljava/lang/String;Ljava/lang/String;Ljava/lang/String;ILkotlin/jvm/internal/DefaultConstructorMarker;)V
     159: invokespecial #409                // Method com/ocutech/editor/model/AckResponse."<init>":(ZLjava/lang/String;IZLjava/lang/String;Lcom/ocutech/editor/model/ApiError;)V
     162: astore        4
     164: nop
     165: iconst_0
     166: istore        5
     168: aload_3
     169: invokevirtual #106                // Method com/ocutech/editor/model/JsonCodec.getJson:()Lkotlinx/serialization/json/Json;
     172: astore        6
     174: aload         4
     176: astore        7
     178: iconst_0
     179: istore        8
     181: aload         6
     183: aload         6
     185: invokevirtual #112                // Method kotlinx/serialization/json/Json.getSerializersModule:()Lkotlinx/serialization/modules/SerializersModule;
     188: pop
     189: getstatic     #412                // Field com/ocutech/editor/model/AckResponse.Companion:Lcom/ocutech/editor/model/AckResponse$Companion;
     192: invokevirtual #415                // Method com/ocutech/editor/model/AckResponse$Companion.serializer:()Lkotlinx/serialization/KSerializer;
     195: checkcast     #178                // class kotlinx/serialization/SerializationStrategy
     198: aload         7
     200: invokevirtual #182                // Method kotlinx/serialization/json/Json.encodeToString:(Lkotlinx/serialization/SerializationStrategy;Ljava/lang/Object;)Ljava/lang/String;
     203: nop
     204: areturn

  public static final java.lang.String releaseAll();
    Code:
       0: getstatic     #76                 // Field INSTANCE:Lcom/ocutech/editor/api/UnityVideoEditor;
       3: invokespecial #255                // Method ensureRuntime:()Lcom/ocutech/editor/api/UnityVideoEditor$Runtime;
       6: dup
       7: ifnonnull     87
      10: pop
      11: getstatic     #102                // Field com/ocutech/editor/model/JsonCodec.INSTANCE:Lcom/ocutech/editor/model/JsonCodec;
      14: astore_2
      15: new           #404                // class com/ocutech/editor/model/AckResponse
      18: dup
      19: iconst_0
      20: ldc           #55                 // String 0.1.1-threadfix
      22: iconst_1
      23: iconst_0
      24: ldc_w         #432                // String Call initialize() before releaseAll().
      27: new           #147                // class com/ocutech/editor/model/ApiError
      30: dup
      31: ldc_w         #329                // String NOT_INITIALIZED
      34: ldc_w         #432                // String Call initialize() before releaseAll().
      37: aconst_null
      38: iconst_4
      39: aconst_null
      40: invokespecial #194                // Method com/ocutech/editor/model/ApiError."<init>":(Ljava/lang/String;Ljava/lang/String;Ljava/lang/String;ILkotlin/jvm/internal/DefaultConstructorMarker;)V
      43: invokespecial #409                // Method com/ocutech/editor/model/AckResponse."<init>":(ZLjava/lang/String;IZLjava/lang/String;Lcom/ocutech/editor/model/ApiError;)V
      46: astore_3
      47: nop
      48: iconst_0
      49: istore        4
      51: aload_2
      52: invokevirtual #106                // Method com/ocutech/editor/model/JsonCodec.getJson:()Lkotlinx/serialization/json/Json;
      55: astore        5
      57: aload_3
      58: astore        6
      60: iconst_0
      61: istore        7
      63: aload         5
      65: aload         5
      67: invokevirtual #112                // Method kotlinx/serialization/json/Json.getSerializersModule:()Lkotlinx/serialization/modules/SerializersModule;
      70: pop
      71: getstatic     #412                // Field com/ocutech/editor/model/AckResponse.Companion:Lcom/ocutech/editor/model/AckResponse$Companion;
      74: invokevirtual #415                // Method com/ocutech/editor/model/AckResponse$Companion.serializer:()Lkotlinx/serialization/KSerializer;
      77: checkcast     #178                // class kotlinx/serialization/SerializationStrategy
      80: aload         6
      82: invokevirtual #182                // Method kotlinx/serialization/json/Json.encodeToString:(Lkotlinx/serialization/SerializationStrategy;Ljava/lang/Object;)Ljava/lang/String;
      85: nop
      86: areturn
      87: astore_0
      88: aload_0
      89: invokevirtual #358                // Method com/ocutech/editor/api/UnityVideoEditor$Runtime.getManager:()Lcom/ocutech/editor/export/ExportJobManager;
      92: invokevirtual #435                // Method com/ocutech/editor/export/ExportJobManager.releaseAll:()I
      95: istore_1
      96: getstatic     #102                // Field com/ocutech/editor/model/JsonCodec.INSTANCE:Lcom/ocutech/editor/model/JsonCodec;
      99: astore_2
     100: new           #404                // class com/ocutech/editor/model/AckResponse
     103: dup
     104: iconst_1
     105: ldc           #55                 // String 0.1.1-threadfix
     107: iconst_1
     108: iconst_1
     109: iload_1
     110: invokedynamic #440,  0            // InvokeDynamic #1:makeConcatWithConstants:(I)Ljava/lang/String;
     115: aconst_null
     116: bipush        32
     118: aconst_null
     119: invokespecial #443                // Method com/ocutech/editor/model/AckResponse."<init>":(ZLjava/lang/String;IZLjava/lang/String;Lcom/ocutech/editor/model/ApiError;ILkotlin/jvm/internal/DefaultConstructorMarker;)V
     122: astore_3
     123: nop
     124: iconst_0
     125: istore        4
     127: aload_2
     128: invokevirtual #106                // Method com/ocutech/editor/model/JsonCodec.getJson:()Lkotlinx/serialization/json/Json;
     131: astore        5
     133: aload_3
     134: astore        6
     136: iconst_0
     137: istore        7
     139: aload         5
     141: aload         5
     143: invokevirtual #112                // Method kotlinx/serialization/json/Json.getSerializersModule:()Lkotlinx/serialization/modules/SerializersModule;
     146: pop
     147: getstatic     #412                // Field com/ocutech/editor/model/AckResponse.Companion:Lcom/ocutech/editor/model/AckResponse$Companion;
     150: invokevirtual #415                // Method com/ocutech/editor/model/AckResponse$Companion.serializer:()Lkotlinx/serialization/KSerializer;
     153: checkcast     #178                // class kotlinx/serialization/SerializationStrategy
     156: aload         6
     158: invokevirtual #182                // Method kotlinx/serialization/json/Json.encodeToString:(Lkotlinx/serialization/SerializationStrategy;Ljava/lang/Object;)Ljava/lang/String;
     161: nop
     162: areturn

  private final com.ocutech.editor.api.UnityVideoEditor$Runtime ensureRuntime();
    Code:
       0: getstatic     #223                // Field runtime:Lcom/ocutech/editor/api/UnityVideoEditor$Runtime;
       3: dup
       4: ifnonnull     137
       7: pop
       8: getstatic     #198                // Field lock:Ljava/lang/Object;
      11: astore_1
      12: aload_1
      13: monitorenter
      14: nop
      15: iconst_0
      16: istore_2
      17: getstatic     #223                // Field runtime:Lcom/ocutech/editor/api/UnityVideoEditor$Runtime;
      20: dup
      21: ifnonnull     124
      24: pop
      25: getstatic     #76                 // Field INSTANCE:Lcom/ocutech/editor/api/UnityVideoEditor;
      28: astore_3
      29: iconst_0
      30: istore        4
      32: aload_3
      33: invokespecial #185                // Method resolveAppContext:()Landroid/content/Context;
      36: dup
      37: ifnonnull     45
      40: pop
      41: aconst_null
      42: goto          125
      45: astore        5
      47: new           #50                 // class com/ocutech/editor/api/UnityVideoEditor$Runtime
      50: dup
      51: new           #92                 // class com/ocutech/editor/model/EditorConfig
      54: dup
      55: iconst_0
      56: iconst_0
      57: iconst_0
      58: bipush        7
      60: aconst_null
      61: invokespecial #95                 // Method com/ocutech/editor/model/EditorConfig."<init>":(IZZILkotlin/jvm/internal/DefaultConstructorMarker;)V
      64: new           #200                // class com/ocutech/editor/export/ExportJobManager
      67: dup
      68: aload         5
      70: new           #202                // class com/ocutech/editor/export/ExportRuntimeConfig
      73: dup
      74: ldc           #55                 // String 0.1.1-threadfix
      76: iconst_1
      77: iconst_0
      78: iconst_0
      79: bipush        12
      81: aconst_null
      82: invokespecial #447                // Method com/ocutech/editor/export/ExportRuntimeConfig."<init>":(Ljava/lang/String;IZZILkotlin/jvm/internal/DefaultConstructorMarker;)V
      85: aconst_null
      86: aconst_null
      87: aconst_null
      88: bipush        28
      90: aconst_null
      91: invokespecial #215                // Method com/ocutech/editor/export/ExportJobManager."<init>":(Landroid/content/Context;Lcom/ocutech/editor/export/ExportRuntimeConfig;Lcom/ocutech/editor/core/ProjectPlanner;Lcom/ocutech/editor/export/ExportExecutor;Lkotlinx/coroutines/CoroutineDispatcher;ILkotlin/jvm/internal/DefaultConstructorMarker;)V
      94: new           #217                // class com/ocutech/editor/core/ProjectPlanner
      97: dup
      98: invokespecial #218                // Method com/ocutech/editor/core/ProjectPlanner."<init>":()V
     101: aload         5
     103: invokespecial #221                // Method com/ocutech/editor/api/UnityVideoEditor$Runtime."<init>":(Lcom/ocutech/editor/model/EditorConfig;Lcom/ocutech/editor/export/ExportJobManager;Lcom/ocutech/editor/core/ProjectPlanner;Landroid/content/Context;)V
     106: astore        6
     108: aload         6
     110: astore        7
     112: iconst_0
     113: istore        8
     115: aload         7
     117: putstatic     #223                // Field runtime:Lcom/ocutech/editor/api/UnityVideoEditor$Runtime;
     120: aload         6
     122: nop
     123: nop
     124: nop
     125: astore_2
     126: aload_1
     127: monitorexit
     128: aload_2
     129: goto          137
     132: astore_3
     133: aload_1
     134: monitorexit
     135: aload_3
     136: athrow
     137: areturn
    Exception table:
       from    to  target type
          14   126   132   any
         132   133   132   any

  private final com.ocutech.editor.model.EditorProjectDocument parseProject(java.lang.String);
    Code:
       0: aload_0
       1: astore_2
       2: nop
       3: getstatic     #82                 // Field kotlin/Result.Companion:Lkotlin/Result$Companion;
       6: pop
       7: aload_2
       8: checkcast     #2                  // class com/ocutech/editor/api/UnityVideoEditor
      11: astore_3
      12: iconst_0
      13: istore        4
      15: getstatic     #102                // Field com/ocutech/editor/model/JsonCodec.INSTANCE:Lcom/ocutech/editor/model/JsonCodec;
      18: astore        5
      20: aload_1
      21: astore        6
      23: iconst_0
      24: istore        7
      26: aload         5
      28: invokevirtual #106                // Method com/ocutech/editor/model/JsonCodec.getJson:()Lkotlinx/serialization/json/Json;
      31: astore        8
      33: aload         6
      35: astore        9
      37: iconst_0
      38: istore        10
      40: aload         8
      42: aload         8
      44: invokevirtual #112                // Method kotlinx/serialization/json/Json.getSerializersModule:()Lkotlinx/serialization/modules/SerializersModule;
      47: pop
      48: getstatic     #455                // Field com/ocutech/editor/model/EditorProjectDocument.Companion:Lcom/ocutech/editor/model/EditorProjectDocument$Companion;
      51: invokevirtual #458                // Method com/ocutech/editor/model/EditorProjectDocument$Companion.serializer:()Lkotlinx/serialization/KSerializer;
      54: checkcast     #123                // class kotlinx/serialization/DeserializationStrategy
      57: aload         9
      59: invokevirtual #127                // Method kotlinx/serialization/json/Json.decodeFromString:(Lkotlinx/serialization/DeserializationStrategy;Ljava/lang/String;)Ljava/lang/Object;
      62: nop
      63: checkcast     #264                // class com/ocutech/editor/model/EditorProjectDocument
      66: nop
      67: invokestatic  #131                // Method kotlin/Result."constructor-impl":(Ljava/lang/Object;)Ljava/lang/Object;
      70: astore_3
      71: goto          89
      74: astore        4
      76: getstatic     #82                 // Field kotlin/Result.Companion:Lkotlin/Result$Companion;
      79: pop
      80: aload         4
      82: invokestatic  #137                // Method kotlin/ResultKt.createFailure:(Ljava/lang/Throwable;)Ljava/lang/Object;
      85: invokestatic  #131                // Method kotlin/Result."constructor-impl":(Ljava/lang/Object;)Ljava/lang/Object;
      88: astore_3
      89: aload_3
      90: astore_2
      91: aload_2
      92: invokestatic  #462                // Method kotlin/Result."isFailure-impl":(Ljava/lang/Object;)Z
      95: ifeq          102
      98: aconst_null
      99: goto          103
     102: aload_2
     103: checkcast     #264                // class com/ocutech/editor/model/EditorProjectDocument
     106: areturn
    Exception table:
       from    to  target type
           2    71    74   Class java/lang/Throwable

  private final java.lang.String notInitializedValidateResponse();
    Code:
       0: getstatic     #102                // Field com/ocutech/editor/model/JsonCodec.INSTANCE:Lcom/ocutech/editor/model/JsonCodec;
       3: astore_1
       4: new           #305                // class com/ocutech/editor/model/ValidateProjectResponse
       7: dup
       8: iconst_0
       9: ldc           #55                 // String 0.1.1-threadfix
      11: iconst_1
      12: new           #285                // class com/ocutech/editor/model/ValidationReport
      15: dup
      16: aconst_null
      17: aconst_null
      18: aconst_null
      19: lconst_0
      20: bipush        15
      22: aconst_null
      23: invokespecial #467                // Method com/ocutech/editor/model/ValidationReport."<init>":(Ljava/util/List;Ljava/util/List;Ljava/util/List;JILkotlin/jvm/internal/DefaultConstructorMarker;)V
      26: new           #147                // class com/ocutech/editor/model/ApiError
      29: dup
      30: ldc_w         #329                // String NOT_INITIALIZED
      33: ldc_w         #469                // String Call initialize() before validateProject().
      36: aconst_null
      37: iconst_4
      38: aconst_null
      39: invokespecial #194                // Method com/ocutech/editor/model/ApiError."<init>":(Ljava/lang/String;Ljava/lang/String;Ljava/lang/String;ILkotlin/jvm/internal/DefaultConstructorMarker;)V
      42: invokespecial #472                // Method com/ocutech/editor/model/ValidateProjectResponse."<init>":(ZLjava/lang/String;ILcom/ocutech/editor/model/ValidationReport;Lcom/ocutech/editor/model/ApiError;)V
      45: astore_2
      46: nop
      47: iconst_0
      48: istore_3
      49: aload_1
      50: invokevirtual #106                // Method com/ocutech/editor/model/JsonCodec.getJson:()Lkotlinx/serialization/json/Json;
      53: astore        4
      55: aload_2
      56: astore        5
      58: iconst_0
      59: istore        6
      61: aload         4
      63: aload         4
      65: invokevirtual #112                // Method kotlinx/serialization/json/Json.getSerializersModule:()Lkotlinx/serialization/modules/SerializersModule;
      68: pop
      69: getstatic     #316                // Field com/ocutech/editor/model/ValidateProjectResponse.Companion:Lcom/ocutech/editor/model/ValidateProjectResponse$Companion;
      72: invokevirtual #319                // Method com/ocutech/editor/model/ValidateProjectResponse$Companion.serializer:()Lkotlinx/serialization/KSerializer;
      75: checkcast     #178                // class kotlinx/serialization/SerializationStrategy
      78: aload         5
      80: invokevirtual #182                // Method kotlinx/serialization/json/Json.encodeToString:(Lkotlinx/serialization/SerializationStrategy;Ljava/lang/Object;)Ljava/lang/String;
      83: nop
      84: areturn

  private final java.lang.String invalidProjectValidateResponse();
    Code:
       0: getstatic     #102                // Field com/ocutech/editor/model/JsonCodec.INSTANCE:Lcom/ocutech/editor/model/JsonCodec;
       3: astore_1
       4: new           #305                // class com/ocutech/editor/model/ValidateProjectResponse
       7: dup
       8: iconst_0
       9: ldc           #55                 // String 0.1.1-threadfix
      11: iconst_1
      12: new           #285                // class com/ocutech/editor/model/ValidationReport
      15: dup
      16: new           #353                // class com/ocutech/editor/model/ValidationIssue
      19: dup
      20: ldc_w         #342                // String INVALID_PROJECT_JSON
      23: ldc_w         #344                // String Project JSON is malformed.
      26: aconst_null
      27: iconst_4
      28: aconst_null
      29: invokespecial #473                // Method com/ocutech/editor/model/ValidationIssue."<init>":(Ljava/lang/String;Ljava/lang/String;Ljava/lang/String;ILkotlin/jvm/internal/DefaultConstructorMarker;)V
      32: invokestatic  #477                // Method kotlin/collections/CollectionsKt.listOf:(Ljava/lang/Object;)Ljava/util/List;
      35: aconst_null
      36: aconst_null
      37: lconst_0
      38: bipush        14
      40: aconst_null
      41: invokespecial #467                // Method com/ocutech/editor/model/ValidationReport."<init>":(Ljava/util/List;Ljava/util/List;Ljava/util/List;JILkotlin/jvm/internal/DefaultConstructorMarker;)V
      44: new           #147                // class com/ocutech/editor/model/ApiError
      47: dup
      48: ldc_w         #342                // String INVALID_PROJECT_JSON
      51: ldc_w         #344                // String Project JSON is malformed.
      54: aconst_null
      55: iconst_4
      56: aconst_null
      57: invokespecial #194                // Method com/ocutech/editor/model/ApiError."<init>":(Ljava/lang/String;Ljava/lang/String;Ljava/lang/String;ILkotlin/jvm/internal/DefaultConstructorMarker;)V
      60: invokespecial #472                // Method com/ocutech/editor/model/ValidateProjectResponse."<init>":(ZLjava/lang/String;ILcom/ocutech/editor/model/ValidationReport;Lcom/ocutech/editor/model/ApiError;)V
      63: astore_2
      64: nop
      65: iconst_0
      66: istore_3
      67: aload_1
      68: invokevirtual #106                // Method com/ocutech/editor/model/JsonCodec.getJson:()Lkotlinx/serialization/json/Json;
      71: astore        4
      73: aload_2
      74: astore        5
      76: iconst_0
      77: istore        6
      79: aload         4
      81: aload         4
      83: invokevirtual #112                // Method kotlinx/serialization/json/Json.getSerializersModule:()Lkotlinx/serialization/modules/SerializersModule;
      86: pop
      87: getstatic     #316                // Field com/ocutech/editor/model/ValidateProjectResponse.Companion:Lcom/ocutech/editor/model/ValidateProjectResponse$Companion;
      90: invokevirtual #319                // Method com/ocutech/editor/model/ValidateProjectResponse$Companion.serializer:()Lkotlinx/serialization/KSerializer;
      93: checkcast     #178                // class kotlinx/serialization/SerializationStrategy
      96: aload         5
      98: invokevirtual #182                // Method kotlinx/serialization/json/Json.encodeToString:(Lkotlinx/serialization/SerializationStrategy;Ljava/lang/Object;)Ljava/lang/String;
     101: nop
     102: areturn

  private final android.content.Context resolveAppContext();
    Code:
       0: nop
       1: ldc_w         #479                // String android.app.ActivityThread
       4: invokestatic  #483                // Method java/lang/Class.forName:(Ljava/lang/String;)Ljava/lang/Class;
       7: astore_1
       8: aload_1
       9: ldc_w         #485                // String currentApplication
      12: iconst_0
      13: anewarray     #161                // class java/lang/Class
      16: invokevirtual #489                // Method java/lang/Class.getMethod:(Ljava/lang/String;[Ljava/lang/Class;)Ljava/lang/reflect/Method;
      19: aconst_null
      20: iconst_0
      21: anewarray     #4                  // class java/lang/Object
      24: invokevirtual #495                // Method java/lang/reflect/Method.invoke:(Ljava/lang/Object;[Ljava/lang/Object;)Ljava/lang/Object;
      27: astore_3
      28: aload_3
      29: instanceof    #497                // class android/app/Application
      32: ifeq          42
      35: aload_3
      36: checkcast     #497                // class android/app/Application
      39: goto          43
      42: aconst_null
      43: astore_2
      44: aload_2
      45: dup
      46: ifnull        55
      49: invokevirtual #500                // Method android/app/Application.getApplicationContext:()Landroid/content/Context;
      52: goto          57
      55: pop
      56: aconst_null
      57: astore_1
      58: goto          64
      61: astore_2
      62: aconst_null
      63: astore_1
      64: aload_1
      65: areturn
    Exception table:
       from    to  target type
           0    58    61   Class java/lang/Throwable

  static {};
    Code:
       0: new           #2                  // class com/ocutech/editor/api/UnityVideoEditor
       3: dup
       4: invokespecial #507                // Method "<init>":()V
       7: putstatic     #76                 // Field INSTANCE:Lcom/ocutech/editor/api/UnityVideoEditor;
      10: new           #4                  // class java/lang/Object
      13: dup
      14: invokespecial #62                 // Method java/lang/Object."<init>":()V
      17: putstatic     #198                // Field lock:Ljava/lang/Object;
      20: bipush        12
      22: anewarray     #97                 // class java/lang/String
      25: astore_0
      26: aload_0
      27: iconst_0
      28: ldc_w         #509                // String sequential_video_image_timeline
      31: aastore
      32: aload_0
      33: iconst_1
      34: ldc_w         #511                // String clip_trim
      37: aastore
      38: aload_0
      39: iconst_2
      40: ldc_w         #513                // String clip_mute_and_volume
      43: aastore
      44: aload_0
      45: iconst_3
      46: ldc_w         #515                // String background_music_lane
      49: aastore
      50: aload_0
      51: iconst_4
      52: ldc_w         #517                // String color_controls
      55: aastore
      56: aload_0
      57: iconst_5
      58: ldc_w         #519                // String lut_pipeline
      61: aastore
      62: aload_0
      63: bipush        6
      65: ldc_w         #521                // String overlay_watermark_sticker
      68: aastore
      69: aload_0
      70: bipush        7
      72: ldc_w         #523                // String dip_to_black_and_fade_from_black
      75: aastore
      76: aload_0
      77: bipush        8
      79: ldc_w         #525                // String media_store_gallery_bridge
      82: aastore
      83: aload_0
      84: bipush        9
      86: ldc_w         #527                // String multi_sequence_composition
      89: aastore
      90: aload_0
      91: bipush        10
      93: ldc_w         #529                // String job_progress_polling
      96: aastore
      97: aload_0
      98: bipush        11
     100: ldc_w         #531                // String structured_errors
     103: aastore
     104: aload_0
     105: invokestatic  #534                // Method kotlin/collections/CollectionsKt.listOf:([Ljava/lang/Object;)Ljava/util/List;
     108: putstatic     #230                // Field SUPPORTED_FEATURES:Ljava/util/List;
     111: return
}
