Compiled from "ExportExecutor.kt"
final class com.ocutech.editor.export.Media3ExportExecutor$export$2 extends kotlin.coroutines.jvm.internal.SuspendLambda implements kotlin.jvm.functions.Function2<kotlinx.coroutines.CoroutineScope, kotlin.coroutines.Continuation<? super com.ocutech.editor.export.ExportOutput>, java.lang.Object> {
  java.lang.Object L$1;

  java.lang.Object L$2;

  java.lang.Object L$3;

  java.lang.Object L$4;

  java.lang.Object L$5;

  java.lang.Object L$6;

  java.lang.Object L$7;

  java.lang.Object L$8;

  java.lang.Object L$9;

  int I$0;

  int label;

  private java.lang.Object L$0;

  final com.ocutech.editor.core.PlannedProject $plan;

  final com.ocutech.editor.export.Media3ExportExecutor this$0;

  final java.lang.String $jobId;

  final kotlin.jvm.functions.Function1<java.lang.Integer, kotlin.Unit> $onProgress;

  com.ocutech.editor.export.Media3ExportExecutor$export$2(com.ocutech.editor.core.PlannedProject, com.ocutech.editor.export.Media3ExportExecutor, java.lang.String, kotlin.jvm.functions.Function1<? super java.lang.Integer, kotlin.Unit>, kotlin.coroutines.Continuation<? super com.ocutech.editor.export.Media3ExportExecutor$export$2>);
    Code:
       0: aload_0
       1: aload_1
       2: putfield      #88                 // Field $plan:Lcom/ocutech/editor/core/PlannedProject;
       5: aload_0
       6: aload_2
       7: putfield      #90                 // Field this$0:Lcom/ocutech/editor/export/Media3ExportExecutor;
      10: aload_0
      11: aload_3
      12: putfield      #92                 // Field $jobId:Ljava/lang/String;
      15: aload_0
      16: aload         4
      18: putfield      #94                 // Field $onProgress:Lkotlin/jvm/functions/Function1;
      21: aload_0
      22: iconst_2
      23: aload         5
      25: invokespecial #97                 // Method kotlin/coroutines/jvm/internal/SuspendLambda."<init>":(ILkotlin/coroutines/Continuation;)V
      28: return

  public final java.lang.Object invokeSuspend(java.lang.Object);
    Code:
       0: aload_0
       1: getfield      #109                // Field L$0:Ljava/lang/Object;
       4: checkcast     #111                // class kotlinx/coroutines/CoroutineScope
       7: astore_2
       8: invokestatic  #117                // Method kotlin/coroutines/intrinsics/IntrinsicsKt.getCOROUTINE_SUSPENDED:()Ljava/lang/Object;
      11: astore        16
      13: aload_0
      14: getfield      #119                // Field label:I
      17: tableswitch   { // 0 to 1
                     0: 40
                     1: 433
               default: 875
          }
      40: aload_1
      41: invokestatic  #127                // Method kotlin/ResultKt.throwOnFailure:(Ljava/lang/Object;)V
      44: new           #129                // class java/util/ArrayList
      47: dup
      48: invokespecial #132                // Method java/util/ArrayList."<init>":()V
      51: checkcast     #134                // class java/util/List
      54: astore_3
      55: aload_0
      56: getfield      #88                 // Field $plan:Lcom/ocutech/editor/core/PlannedProject;
      59: invokevirtual #140                // Method com/ocutech/editor/core/PlannedProject.getSource:()Lcom/ocutech/editor/model/EditorProjectDocument;
      62: invokevirtual #146                // Method com/ocutech/editor/model/EditorProjectDocument.getExport:()Lcom/ocutech/editor/model/ExportSpec;
      65: invokevirtual #152                // Method com/ocutech/editor/model/ExportSpec.getOutputUri:()Ljava/lang/String;
      68: astore        4
      70: new           #154                // class java/io/File
      73: dup
      74: aload_0
      75: getfield      #90                 // Field this$0:Lcom/ocutech/editor/export/Media3ExportExecutor;
      78: invokestatic  #158                // Method com/ocutech/editor/export/Media3ExportExecutor.access$getContext$p:(Lcom/ocutech/editor/export/Media3ExportExecutor;)Landroid/content/Context;
      81: invokevirtual #164                // Method android/content/Context.getCacheDir:()Ljava/io/File;
      84: aload_0
      85: getfield      #92                 // Field $jobId:Ljava/lang/String;
      88: invokedynamic #176,  0            // InvokeDynamic #0:makeConcatWithConstants:(Ljava/lang/String;)Ljava/lang/String;
      93: invokespecial #179                // Method java/io/File."<init>":(Ljava/io/File;Ljava/lang/String;)V
      96: astore        5
      98: aload         5
     100: invokevirtual #183                // Method java/io/File.exists:()Z
     103: ifeq          112
     106: aload         5
     108: invokevirtual #186                // Method java/io/File.delete:()Z
     111: pop
     112: aload_0
     113: getfield      #90                 // Field this$0:Lcom/ocutech/editor/export/Media3ExportExecutor;
     116: aload_0
     117: getfield      #88                 // Field $plan:Lcom/ocutech/editor/core/PlannedProject;
     120: aload_3
     121: invokestatic  #192                // Method com/ocutech/editor/export/Media3ExportExecutor.access$buildComposition:(Lcom/ocutech/editor/export/Media3ExportExecutor;Lcom/ocutech/editor/core/PlannedProject;Ljava/util/List;)Landroidx/media3/transformer/Composition;
     124: astore        6
     126: new           #194                // class java/util/concurrent/atomic/AtomicBoolean
     129: dup
     130: iconst_0
     131: invokespecial #197                // Method java/util/concurrent/atomic/AtomicBoolean."<init>":(Z)V
     134: astore        7
     136: new           #199                // class java/util/concurrent/atomic/AtomicReference
     139: dup
     140: aconst_null
     141: invokespecial #201                // Method java/util/concurrent/atomic/AtomicReference."<init>":(Ljava/lang/Object;)V
     144: astore        8
     146: new           #203                // class androidx/media3/transformer/ProgressHolder
     149: dup
     150: invokespecial #204                // Method androidx/media3/transformer/ProgressHolder."<init>":()V
     153: astore        9
     155: new           #65                 // class androidx/media3/transformer/Transformer$Builder
     158: dup
     159: aload_0
     160: getfield      #90                 // Field this$0:Lcom/ocutech/editor/export/Media3ExportExecutor;
     163: invokestatic  #158                // Method com/ocutech/editor/export/Media3ExportExecutor.access$getContext$p:(Lcom/ocutech/editor/export/Media3ExportExecutor;)Landroid/content/Context;
     166: invokespecial #207                // Method androidx/media3/transformer/Transformer$Builder."<init>":(Landroid/content/Context;)V
     169: invokestatic  #213                // Method android/os/Looper.getMainLooper:()Landroid/os/Looper;
     172: invokevirtual #217                // Method androidx/media3/transformer/Transformer$Builder.setLooper:(Landroid/os/Looper;)Landroidx/media3/transformer/Transformer$Builder;
     175: aload_0
     176: getfield      #88                 // Field $plan:Lcom/ocutech/editor/core/PlannedProject;
     179: invokevirtual #140                // Method com/ocutech/editor/core/PlannedProject.getSource:()Lcom/ocutech/editor/model/EditorProjectDocument;
     182: invokevirtual #146                // Method com/ocutech/editor/model/EditorProjectDocument.getExport:()Lcom/ocutech/editor/model/ExportSpec;
     185: invokevirtual #220                // Method com/ocutech/editor/model/ExportSpec.getAudioMimeType:()Ljava/lang/String;
     188: invokevirtual #224                // Method androidx/media3/transformer/Transformer$Builder.setAudioMimeType:(Ljava/lang/String;)Landroidx/media3/transformer/Transformer$Builder;
     191: aload_0
     192: getfield      #88                 // Field $plan:Lcom/ocutech/editor/core/PlannedProject;
     195: invokevirtual #140                // Method com/ocutech/editor/core/PlannedProject.getSource:()Lcom/ocutech/editor/model/EditorProjectDocument;
     198: invokevirtual #146                // Method com/ocutech/editor/model/EditorProjectDocument.getExport:()Lcom/ocutech/editor/model/ExportSpec;
     201: invokevirtual #227                // Method com/ocutech/editor/model/ExportSpec.getVideoMimeType:()Ljava/lang/String;
     204: invokevirtual #230                // Method androidx/media3/transformer/Transformer$Builder.setVideoMimeType:(Ljava/lang/String;)Landroidx/media3/transformer/Transformer$Builder;
     207: iconst_1
     208: invokevirtual #234                // Method androidx/media3/transformer/Transformer$Builder.setEnsureFileStartsOnVideoFrameEnabled:(Z)Landroidx/media3/transformer/Transformer$Builder;
     211: ldc2_w        #235                // long 1500l
     214: invokevirtual #240                // Method androidx/media3/transformer/Transformer$Builder.setMaxDelayBetweenMuxerSamplesMs:(J)Landroidx/media3/transformer/Transformer$Builder;
     217: invokevirtual #244                // Method androidx/media3/transformer/Transformer$Builder.build:()Landroidx/media3/transformer/Transformer;
     220: dup
     221: ldc           #246                // String build(...)
     223: invokestatic  #252                // Method kotlin/jvm/internal/Intrinsics.checkNotNullExpressionValue:(Ljava/lang/Object;Ljava/lang/String;)V
     226: astore        10
     228: aload_0
     229: getfield      #90                 // Field this$0:Lcom/ocutech/editor/export/Media3ExportExecutor;
     232: invokestatic  #256                // Method com/ocutech/editor/export/Media3ExportExecutor.access$getActiveTransformers$p:(Lcom/ocutech/editor/export/Media3ExportExecutor;)Ljava/util/concurrent/ConcurrentHashMap;
     235: checkcast     #258                // class java/util/Map
     238: aload_0
     239: getfield      #92                 // Field $jobId:Ljava/lang/String;
     242: aload         10
     244: invokeinterface #262,  3          // InterfaceMethod java/util/Map.put:(Ljava/lang/Object;Ljava/lang/Object;)Ljava/lang/Object;
     249: pop
     250: nop
     251: new           #264                // class com/ocutech/editor/export/Media3ExportExecutor$export$2$listener$1
     254: dup
     255: aload         7
     257: aload         8
     259: aload_3
     260: invokespecial #267                // Method com/ocutech/editor/export/Media3ExportExecutor$export$2$listener$1."<init>":(Ljava/util/concurrent/atomic/AtomicBoolean;Ljava/util/concurrent/atomic/AtomicReference;Ljava/util/List;)V
     263: astore        11
     265: aload         10
     267: aload         11
     269: checkcast     #70                 // class androidx/media3/transformer/Transformer$Listener
     272: invokevirtual #271                // Method androidx/media3/transformer/Transformer.addListener:(Landroidx/media3/transformer/Transformer$Listener;)V
     275: nop
     276: aload         10
     278: aload         6
     280: aload         5
     282: invokevirtual #274                // Method java/io/File.getAbsolutePath:()Ljava/lang/String;
     285: invokevirtual #278                // Method androidx/media3/transformer/Transformer.start:(Landroidx/media3/transformer/Composition;Ljava/lang/String;)V
     288: aload_2
     289: invokestatic  #286                // Method kotlinx/coroutines/CoroutineScopeKt.isActive:(Lkotlinx/coroutines/CoroutineScope;)Z
     292: ifeq          529
     295: aload         7
     297: invokevirtual #289                // Method java/util/concurrent/atomic/AtomicBoolean.get:()Z
     300: ifne          529
     303: aload         10
     305: aload         9
     307: invokevirtual #293                // Method androidx/media3/transformer/Transformer.getProgress:(Landroidx/media3/transformer/ProgressHolder;)I
     310: istore        12
     312: iload         12
     314: iconst_2
     315: if_icmpne     342
     318: aload_0
     319: getfield      #94                 // Field $onProgress:Lkotlin/jvm/functions/Function1;
     322: aload         9
     324: getfield      #296                // Field androidx/media3/transformer/ProgressHolder.progress:I
     327: iconst_0
     328: bipush        100
     330: invokestatic  #302                // Method kotlin/ranges/RangesKt.coerceIn:(III)I
     333: invokestatic  #308                // Method kotlin/coroutines/jvm/internal/Boxing.boxInt:(I)Ljava/lang/Integer;
     336: invokeinterface #313,  2          // InterfaceMethod kotlin/jvm/functions/Function1.invoke:(Ljava/lang/Object;)Ljava/lang/Object;
     341: pop
     342: ldc2_w        #314                // long 200l
     345: aload_0
     346: checkcast     #317                // class kotlin/coroutines/Continuation
     349: aload_0
     350: aload_2
     351: putfield      #109                // Field L$0:Ljava/lang/Object;
     354: aload_0
     355: aload_3
     356: putfield      #319                // Field L$1:Ljava/lang/Object;
     359: aload_0
     360: aload         4
     362: putfield      #321                // Field L$2:Ljava/lang/Object;
     365: aload_0
     366: aload         5
     368: putfield      #323                // Field L$3:Ljava/lang/Object;
     371: aload_0
     372: aload         6
     374: invokestatic  #328                // Method kotlin/coroutines/jvm/internal/SpillingKt.nullOutSpilledVariable:(Ljava/lang/Object;)Ljava/lang/Object;
     377: putfield      #330                // Field L$4:Ljava/lang/Object;
     380: aload_0
     381: aload         7
     383: putfield      #332                // Field L$5:Ljava/lang/Object;
     386: aload_0
     387: aload         8
     389: putfield      #334                // Field L$6:Ljava/lang/Object;
     392: aload_0
     393: aload         9
     395: putfield      #336                // Field L$7:Ljava/lang/Object;
     398: aload_0
     399: aload         10
     401: putfield      #338                // Field L$8:Ljava/lang/Object;
     404: aload_0
     405: aload         11
     407: putfield      #340                // Field L$9:Ljava/lang/Object;
     410: aload_0
     411: iload         12
     413: putfield      #342                // Field I$0:I
     416: aload_0
     417: iconst_1
     418: putfield      #119                // Field label:I
     421: invokestatic  #348                // Method kotlinx/coroutines/DelayKt.delay:(JLkotlin/coroutines/Continuation;)Ljava/lang/Object;
     424: dup
     425: aload         16
     427: if_acmpne     525
     430: aload         16
     432: areturn
     433: aload_0
     434: getfield      #342                // Field I$0:I
     437: istore        12
     439: aload_0
     440: getfield      #340                // Field L$9:Ljava/lang/Object;
     443: checkcast     #264                // class com/ocutech/editor/export/Media3ExportExecutor$export$2$listener$1
     446: astore        11
     448: aload_0
     449: getfield      #338                // Field L$8:Ljava/lang/Object;
     452: checkcast     #67                 // class androidx/media3/transformer/Transformer
     455: astore        10
     457: aload_0
     458: getfield      #336                // Field L$7:Ljava/lang/Object;
     461: checkcast     #203                // class androidx/media3/transformer/ProgressHolder
     464: astore        9
     466: aload_0
     467: getfield      #334                // Field L$6:Ljava/lang/Object;
     470: checkcast     #199                // class java/util/concurrent/atomic/AtomicReference
     473: astore        8
     475: aload_0
     476: getfield      #332                // Field L$5:Ljava/lang/Object;
     479: checkcast     #194                // class java/util/concurrent/atomic/AtomicBoolean
     482: astore        7
     484: aload_0
     485: getfield      #330                // Field L$4:Ljava/lang/Object;
     488: checkcast     #280                // class androidx/media3/transformer/Composition
     491: astore        6
     493: aload_0
     494: getfield      #323                // Field L$3:Ljava/lang/Object;
     497: checkcast     #154                // class java/io/File
     500: astore        5
     502: aload_0
     503: getfield      #321                // Field L$2:Ljava/lang/Object;
     506: checkcast     #188                // class java/lang/String
     509: astore        4
     511: aload_0
     512: getfield      #319                // Field L$1:Ljava/lang/Object;
     515: checkcast     #134                // class java/util/List
     518: astore_3
     519: nop
     520: aload_1
     521: invokestatic  #127                // Method kotlin/ResultKt.throwOnFailure:(Ljava/lang/Object;)V
     524: aload_1
     525: pop
     526: goto          288
     529: aload         10
     531: aload         11
     533: checkcast     #70                 // class androidx/media3/transformer/Transformer$Listener
     536: invokevirtual #351                // Method androidx/media3/transformer/Transformer.removeListener:(Landroidx/media3/transformer/Transformer$Listener;)V
     539: goto          557
     542: astore        12
     544: aload         10
     546: aload         11
     548: checkcast     #70                 // class androidx/media3/transformer/Transformer$Listener
     551: invokevirtual #351                // Method androidx/media3/transformer/Transformer.removeListener:(Landroidx/media3/transformer/Transformer$Listener;)V
     554: aload         12
     556: athrow
     557: aload_2
     558: invokestatic  #286                // Method kotlinx/coroutines/CoroutineScopeKt.isActive:(Lkotlinx/coroutines/CoroutineScope;)Z
     561: ifne          575
     564: new           #107                // class java/util/concurrent/CancellationException
     567: dup
     568: ldc_w         #353                // String Export coroutine is no longer active.
     571: invokespecial #356                // Method java/util/concurrent/CancellationException."<init>":(Ljava/lang/String;)V
     574: athrow
     575: aload         8
     577: invokevirtual #358                // Method java/util/concurrent/atomic/AtomicReference.get:()Ljava/lang/Object;
     580: checkcast     #105                // class java/lang/Throwable
     583: dup
     584: ifnull        599
     587: astore        13
     589: aload         13
     591: astore        14
     593: iconst_0
     594: istore        15
     596: aload         14
     598: athrow
     599: pop
     600: aload         7
     602: invokevirtual #289                // Method java/util/concurrent/atomic/AtomicBoolean.get:()Z
     605: ifne          619
     608: new           #360                // class java/lang/IllegalStateException
     611: dup
     612: ldc_w         #362                // String Transformer finished without terminal callback.
     615: invokespecial #363                // Method java/lang/IllegalStateException."<init>":(Ljava/lang/String;)V
     618: athrow
     619: aload         5
     621: invokevirtual #183                // Method java/io/File.exists:()Z
     624: ifeq          637
     627: aload         5
     629: invokevirtual #367                // Method java/io/File.length:()J
     632: lconst_0
     633: lcmp
     634: ifgt          648
     637: new           #360                // class java/lang/IllegalStateException
     640: dup
     641: ldc_w         #369                // String Transformer completed without creating output file.
     644: invokespecial #363                // Method java/lang/IllegalStateException."<init>":(Ljava/lang/String;)V
     647: athrow
     648: aload_0
     649: getfield      #90                 // Field this$0:Lcom/ocutech/editor/export/Media3ExportExecutor;
     652: aload         5
     654: aload         4
     656: invokestatic  #373                // Method com/ocutech/editor/export/Media3ExportExecutor.access$persistOutput:(Lcom/ocutech/editor/export/Media3ExportExecutor;Ljava/io/File;Ljava/lang/String;)Ljava/lang/String;
     659: astore        12
     661: aload_0
     662: getfield      #94                 // Field $onProgress:Lkotlin/jvm/functions/Function1;
     665: bipush        100
     667: invokestatic  #308                // Method kotlin/coroutines/jvm/internal/Boxing.boxInt:(I)Ljava/lang/Integer;
     670: invokeinterface #313,  2          // InterfaceMethod kotlin/jvm/functions/Function1.invoke:(Ljava/lang/Object;)Ljava/lang/Object;
     675: pop
     676: new           #375                // class com/ocutech/editor/export/ExportOutput
     679: dup
     680: aload         12
     682: aload_3
     683: invokespecial #378                // Method com/ocutech/editor/export/ExportOutput."<init>":(Ljava/lang/String;Ljava/util/List;)V
     686: astore        11
     688: aload_0
     689: getfield      #90                 // Field this$0:Lcom/ocutech/editor/export/Media3ExportExecutor;
     692: invokestatic  #256                // Method com/ocutech/editor/export/Media3ExportExecutor.access$getActiveTransformers$p:(Lcom/ocutech/editor/export/Media3ExportExecutor;)Ljava/util/concurrent/ConcurrentHashMap;
     695: aload_0
     696: getfield      #92                 // Field $jobId:Ljava/lang/String;
     699: invokevirtual #383                // Method java/util/concurrent/ConcurrentHashMap.remove:(Ljava/lang/Object;)Ljava/lang/Object;
     702: pop
     703: aload_2
     704: astore        12
     706: nop
     707: getstatic     #389                // Field kotlin/Result.Companion:Lkotlin/Result$Companion;
     710: pop
     711: aload         12
     713: astore        13
     715: iconst_0
     716: istore        14
     718: aload         5
     720: invokevirtual #186                // Method java/io/File.delete:()Z
     723: invokestatic  #393                // Method kotlin/coroutines/jvm/internal/Boxing.boxBoolean:(Z)Ljava/lang/Boolean;
     726: invokestatic  #396                // Method kotlin/Result."constructor-impl":(Ljava/lang/Object;)Ljava/lang/Object;
     729: astore        13
     731: goto          750
     734: astore        14
     736: getstatic     #389                // Field kotlin/Result.Companion:Lkotlin/Result$Companion;
     739: pop
     740: aload         14
     742: invokestatic  #400                // Method kotlin/ResultKt.createFailure:(Ljava/lang/Throwable;)Ljava/lang/Object;
     745: invokestatic  #396                // Method kotlin/Result."constructor-impl":(Ljava/lang/Object;)Ljava/lang/Object;
     748: astore        13
     750: goto          872
     753: astore        12
     755: aload_2
     756: astore        13
     758: nop
     759: getstatic     #389                // Field kotlin/Result.Companion:Lkotlin/Result$Companion;
     762: pop
     763: aload         13
     765: astore        14
     767: iconst_0
     768: istore        15
     770: aload         10
     772: invokevirtual #403                // Method androidx/media3/transformer/Transformer.cancel:()V
     775: getstatic     #409                // Field kotlin/Unit.INSTANCE:Lkotlin/Unit;
     778: invokestatic  #396                // Method kotlin/Result."constructor-impl":(Ljava/lang/Object;)Ljava/lang/Object;
     781: astore        14
     783: goto          802
     786: astore        15
     788: getstatic     #389                // Field kotlin/Result.Companion:Lkotlin/Result$Companion;
     791: pop
     792: aload         15
     794: invokestatic  #400                // Method kotlin/ResultKt.createFailure:(Ljava/lang/Throwable;)Ljava/lang/Object;
     797: invokestatic  #396                // Method kotlin/Result."constructor-impl":(Ljava/lang/Object;)Ljava/lang/Object;
     800: astore        14
     802: aload         12
     804: athrow
     805: astore        12
     807: aload_0
     808: getfield      #90                 // Field this$0:Lcom/ocutech/editor/export/Media3ExportExecutor;
     811: invokestatic  #256                // Method com/ocutech/editor/export/Media3ExportExecutor.access$getActiveTransformers$p:(Lcom/ocutech/editor/export/Media3ExportExecutor;)Ljava/util/concurrent/ConcurrentHashMap;
     814: aload_0
     815: getfield      #92                 // Field $jobId:Ljava/lang/String;
     818: invokevirtual #383                // Method java/util/concurrent/ConcurrentHashMap.remove:(Ljava/lang/Object;)Ljava/lang/Object;
     821: pop
     822: aload_2
     823: astore        13
     825: nop
     826: getstatic     #389                // Field kotlin/Result.Companion:Lkotlin/Result$Companion;
     829: pop
     830: aload         13
     832: astore        14
     834: iconst_0
     835: istore        15
     837: aload         5
     839: invokevirtual #186                // Method java/io/File.delete:()Z
     842: invokestatic  #393                // Method kotlin/coroutines/jvm/internal/Boxing.boxBoolean:(Z)Ljava/lang/Boolean;
     845: invokestatic  #396                // Method kotlin/Result."constructor-impl":(Ljava/lang/Object;)Ljava/lang/Object;
     848: astore        14
     850: goto          869
     853: astore        15
     855: getstatic     #389                // Field kotlin/Result.Companion:Lkotlin/Result$Companion;
     858: pop
     859: aload         15
     861: invokestatic  #400                // Method kotlin/ResultKt.createFailure:(Ljava/lang/Throwable;)Ljava/lang/Object;
     864: invokestatic  #396                // Method kotlin/Result."constructor-impl":(Ljava/lang/Object;)Ljava/lang/Object;
     867: astore        14
     869: aload         12
     871: athrow
     872: aload         11
     874: areturn
     875: new           #360                // class java/lang/IllegalStateException
     878: dup
     879: ldc_w         #411                // String call to \'resume\' before \'invoke\' with coroutine
     882: invokespecial #363                // Method java/lang/IllegalStateException."<init>":(Ljava/lang/String;)V
     885: athrow
    Exception table:
       from    to  target type
         275   424   542   any
         519   529   542   any
         542   544   542   any
         706   731   734   Class java/lang/Throwable
         758   783   786   Class java/lang/Throwable
         250   424   753   Class java/util/concurrent/CancellationException
         519   688   753   Class java/util/concurrent/CancellationException
         825   850   853   Class java/lang/Throwable
         250   424   805   any
         519   688   805   any
         753   805   805   any
         805   807   805   any

  public final kotlin.coroutines.Continuation<kotlin.Unit> create(java.lang.Object, kotlin.coroutines.Continuation<?>);
    Code:
       0: new           #2                  // class com/ocutech/editor/export/Media3ExportExecutor$export$2
       3: dup
       4: aload_0
       5: getfield      #88                 // Field $plan:Lcom/ocutech/editor/core/PlannedProject;
       8: aload_0
       9: getfield      #90                 // Field this$0:Lcom/ocutech/editor/export/Media3ExportExecutor;
      12: aload_0
      13: getfield      #92                 // Field $jobId:Ljava/lang/String;
      16: aload_0
      17: getfield      #94                 // Field $onProgress:Lkotlin/jvm/functions/Function1;
      20: aload_2
      21: invokespecial #434                // Method "<init>":(Lcom/ocutech/editor/core/PlannedProject;Lcom/ocutech/editor/export/Media3ExportExecutor;Ljava/lang/String;Lkotlin/jvm/functions/Function1;Lkotlin/coroutines/Continuation;)V
      24: astore_3
      25: aload_3
      26: aload_1
      27: putfield      #109                // Field L$0:Ljava/lang/Object;
      30: aload_3
      31: checkcast     #317                // class kotlin/coroutines/Continuation
      34: areturn

  public final java.lang.Object invoke(kotlinx.coroutines.CoroutineScope, kotlin.coroutines.Continuation<? super com.ocutech.editor.export.ExportOutput>);
    Code:
       0: aload_0
       1: aload_1
       2: aload_2
       3: invokevirtual #438                // Method create:(Ljava/lang/Object;Lkotlin/coroutines/Continuation;)Lkotlin/coroutines/Continuation;
       6: checkcast     #2                  // class com/ocutech/editor/export/Media3ExportExecutor$export$2
       9: getstatic     #409                // Field kotlin/Unit.INSTANCE:Lkotlin/Unit;
      12: invokevirtual #440                // Method invokeSuspend:(Ljava/lang/Object;)Ljava/lang/Object;
      15: areturn

  public java.lang.Object invoke(java.lang.Object, java.lang.Object);
    Code:
       0: aload_0
       1: aload_1
       2: checkcast     #111                // class kotlinx/coroutines/CoroutineScope
       5: aload_2
       6: checkcast     #317                // class kotlin/coroutines/Continuation
       9: invokevirtual #444                // Method invoke:(Lkotlinx/coroutines/CoroutineScope;Lkotlin/coroutines/Continuation;)Ljava/lang/Object;
      12: areturn
}
